Metadata-Version: 2.1
Name: anglerr
Version: 2
Summary: Gaussian and Binomial distributions
Author-email: emartynov1312@gmail.com
